seven_segment.v
module seven_segment(
    input [3:0] binary_in,
    output reg [6:0] seg_out   // a b c d e f g
);

always @(*) begin
    case (binary_in)
        4'd0: seg_out = 7'b1111110;
        4'd1: seg_out = 7'b0110000;
        4'd2: seg_out = 7'b1101101;
        4'd3: seg_out = 7'b1111001;
        4'd4: seg_out = 7'b0110011;
        4'd5: seg_out = 7'b1011011;
        4'd6: seg_out = 7'b1011111;
        4'd7: seg_out = 7'b1110000;
        4'd8: seg_out = 7'b1111111;
        4'd9: seg_out = 7'b1111011;
        default: seg_out = 7'b0000001; // dash (-)
    endcase
end

endmodule

seven_segment_tb.v
`timescale 1ns/1ps
module seven_segment_tb;

reg [3:0] binary_in;
wire [6:0] seg_out;

seven_segment uut (
    .binary_in(binary_in),
    .seg_out(seg_out)
);

initial begin
    $dumpfile("dump.vcd");
    $dumpvars(0, seven_segment_tb);

    for (binary_in = 0; binary_in < 10; binary_in = binary_in + 1) begin
        #10;
    end

    $finish;
end

endmodule

dump.vcd
$date
	Sat Jul 26 16:58:59 2025
$end
$version
	Icarus Verilog
$end
$timescale
	1ps
$end
$scope module seven_segment_tb $end
$var wire 7 ! seg_out [6:0] $end
$var reg 4 " binary_in [3:0] $end
$scope module uut $end
$var wire 4 # binary_in [3:0] $end
$var reg 7 $ seg_out [6:0] $end
$upscope $end
$upscope $end
$enddefinitions $end
$comment Show the parameter values. $end
$dumpall
$end
#0
$dumpvars
b1111110 $
b0 #
b0 "
b1111110 !
$end
#10000
b110000 !
b110000 $
b1 "
b1 #
#20000
b1101101 !
b1101101 $
b10 "
b10 #
#30000
b1111001 !
b1111001 $
b11 "
b11 #
#40000
b110011 !
b110011 $
b100 "
b100 #
#50000
b1011011 !
b1011011 $
b101 "
b101 #
#60000
b1011111 !
b1011111 $
b110 "
b110 #
#70000
b1110000 !
b1110000 $
b111 "
b111 #
#80000
b1111111 !
b1111111 $
b1000 "
b1000 #
#90000
b1111011 !
b1111011 $
b1001 "
b1001 #
#100000
b1 !
b1 $
b1010 "
b1010 #
